patternforge/__init__.py
patternforge/core.py
patternforge/analysis/__init__.py
patternforge/analysis/anomaly_engine.py
patternforge/analysis/feature_patterns.py
patternforge/analysis/pattern_entropy.py
patternforge/analysis/symbolic_rules.py
patternforge/analysis/topology_engine.py
patternforge/loaders/__init__.py
patternforge/loaders/graph.py
patternforge/loaders/tabular.py
patternforge/loaders/text.py
patternforge/loaders/timeseries.py
patternforge/reporting/__init__.py
patternforge/reporting/dashboards.py
patternforge/reporting/natural_language.py
patternforge/utils/__init__.py
patternforge/utils/plotting.py
patternforge/utils/preprocess.py
patternforge-0.1.0.dist-info/licenses/LICENSE
patternforge-0.1.0.dist-info/METADATA
patternforge-0.1.0.dist-info/WHEEL
patternforge-0.1.0.dist-info/top_level.txt
patternforge-0.1.0.dist-info/RECORD
