Metadata-Version: 2.4
Name: patternforge
Version: 0.1.0
Summary: Universal automatic pattern discovery engine using TDA, information theory, and symbolic AI
Home-page: https://github.com/idrissbado/patternforge
Author: Idriss Olivier Bado
Author-email: Idriss Olivier Bado <idrissbadoolivier@gmail.com>
License: MIT
Project-URL: Homepage, https://github.com/idrissbado/patternforge
Project-URL: Documentation, https://patternforge.readthedocs.io
Project-URL: Repository, https://github.com/idrissbado/patternforge
Project-URL: Issues, https://github.com/idrissbado/patternforge/issues
Keywords: pattern discovery,topological data analysis,TDA,information theory,machine learning,anomaly detection,symbolic AI
Classifier: Development Status :: 3 - Alpha
Classifier: Intended Audience :: Science/Research
Classifier: Intended Audience :: Developers
Classifier: Topic :: Scientific/Engineering :: Artificial Intelligence
Classifier: Topic :: Scientific/Engineering :: Information Analysis
Classifier: License :: OSI Approved :: MIT License
Classifier: Programming Language :: Python :: 3
Classifier: Programming Language :: Python :: 3.8
Classifier: Programming Language :: Python :: 3.9
Classifier: Programming Language :: Python :: 3.10
Classifier: Programming Language :: Python :: 3.11
Requires-Python: >=3.8
License-File: LICENSE
Requires-Dist: numpy>=1.20.0
Requires-Dist: pandas>=1.3.0
Requires-Dist: scikit-learn>=1.0.0
Requires-Dist: scipy>=1.7.0
Requires-Dist: matplotlib>=3.4.0
Requires-Dist: networkx>=2.6.0
Requires-Dist: gudhi>=3.4.0
Provides-Extra: dev
Requires-Dist: pytest>=7.0.0; extra == "dev"
Requires-Dist: pytest-cov>=3.0.0; extra == "dev"
Requires-Dist: black>=22.0.0; extra == "dev"
Requires-Dist: flake8>=4.0.0; extra == "dev"
Requires-Dist: mypy>=0.950; extra == "dev"
Provides-Extra: docs
Requires-Dist: sphinx>=4.5.0; extra == "docs"
Requires-Dist: sphinx-rtd-theme>=1.0.0; extra == "docs"
Provides-Extra: viz
Requires-Dist: plotly>=5.0.0; extra == "viz"
Requires-Dist: seaborn>=0.11.0; extra == "viz"
Dynamic: author
Dynamic: home-page
Dynamic: license-file
Dynamic: requires-python
